lojack_api/__init__.py
lojack_api/api.py
lojack_api/auth.py
lojack_api/device.py
lojack_api/exceptions.py
lojack_api/models.py
lojack_api/py.typed
lojack_api/transport.py
lojack_api-0.6.3.dist-info/licenses/LICENSE
lojack_api-0.6.3.dist-info/METADATA
lojack_api-0.6.3.dist-info/WHEEL
lojack_api-0.6.3.dist-info/top_level.txt
lojack_api-0.6.3.dist-info/RECORD
