Metadata-Version: 2.4
Name: lojack_api
Version: 0.6.3
Summary: An async Python client library for the LoJack API, designed for Home Assistant integrations.
Author: LoJack Clients Contributors
License: MIT
Project-URL: Homepage, https://github.com/devinslick/lojack_api
Project-URL: Bug Tracker, https://github.com/devinslick/lojack_api/issues
Keywords: lojack,home-assistant,async,api-client,vehicle-tracking
Classifier: Development Status :: 4 - Beta
Classifier: Framework :: AsyncIO
Classifier: Intended Audience :: Developers
Classifier: License :: OSI Approved :: MIT License
Classifier: Operating System :: OS Independent
Classifier: Programming Language :: Python :: 3
Classifier: Programming Language :: Python :: 3.10
Classifier: Programming Language :: Python :: 3.11
Classifier: Programming Language :: Python :: 3.12
Classifier: Topic :: Home Automation
Classifier: Topic :: Software Development :: Libraries :: Python Modules
Classifier: Typing :: Typed
Requires-Python: >=3.10
License-File: LICENSE
Requires-Dist: aiohttp<4.0,>=3.8
Provides-Extra: dev
Requires-Dist: pytest>=7.0; extra == "dev"
Requires-Dist: pytest-asyncio>=0.21; extra == "dev"
Requires-Dist: pytest-cov>=4.0; extra == "dev"
Requires-Dist: mypy>=1.0; extra == "dev"
Requires-Dist: ruff>=0.1; extra == "dev"
Requires-Dist: flake8>=4.0; extra == "dev"
Requires-Dist: aioresponses>=0.7; extra == "dev"
Dynamic: license-file
